Matrix_I:O_Operations/matrixops.v
//how to run: iverilog -o matrixops.vvp matrixops.v matrixops_tb.v
// vvp matrixops.vvp

module matrixops (
  input            clk  ,
  input            rst  ,
  input            enter,
  input      [1:0] X    ,
  input      [1:0] Y    ,
  output reg       Z
);

/* Your design goes here. */

//these are the possible states:
parameter [1:0] R = 2'b00;
parameter [1:0] S = 2'b01;
parameter [1:0] IN = 2'b10;
parameter [1:0] OUT = 2'b11;

reg [1:0] cState; //current state
reg [1:0] nState; //next state
reg [1:0] Z_next;

reg [15:0] M; //the matrix

reg [2:0] Cntr; //counter that counts inputs

always @ (posedge clk or posedge rst) begin
  if(rst)
    cState <= R;
  else
    cState <= nState;
    Z <= Z_next;

end
//combinational logic here - next state and eventually output
always @(*) begin
  case(cState)
    R: begin
      //next state is stop after resetting
      nState = S;
    end

    S: begin
      if(enter) begin
        nState = IN;
      end
    end

    IN: begin
      if (Cntr < 5) begin
        nState = IN; // stay in getting input up until you get all
      end
      else begin
        nState = OUT;
      end
    end

    OUT: begin
      nState = OUT;
    end
  default: nState = R;
  endcase

end

always @(posedge clk or posedge rst) begin
  if (rst) begin
    M <= 16'b0; //resetting all of the elements of the matrix
    Cntr <= 0; // reset cntr too
    Z_next <= 1'b0;
    Z <= 1'b0;
  end
  else if (nState == IN && enter) begin //everything ok to start
    M[4*Y+X] <= 1'b1; // filled that element of the matrix
    Cntr <= Cntr + 1;
  end
  else if (nState == OUT && enter) begin
    Z_next <= M[4*Y+X];
  end
  else begin
    Z_next <= Z_next;
  end
end


endmodule

Matrix_I:O_Operations/matrixops_tb.v
module matrixops_tb ();

  //Ports
  reg        clk  ;
  reg        rst  ;
  reg        enter;
  reg  [1:0] X    ;
  reg  [1:0] Y    ;
  wire       Z    ;

  matrixops dut (
    .clk  (clk  ),
    .rst  (rst  ),
    .enter(enter),
    .X    (X    ),
    .Y    (Y    ),
    .Z    (Z    )
  );

  // Half period of our clock signal
  parameter HP = 5;
  // Full period of our clock signal
  parameter FP = (2*HP);

  // For generating the clock signal
  always #HP clk = ~clk;

  initial begin
    //  * Our waveform is saved under this file.
    $dumpfile("matrixops_tb.vcd");

    // * Get the variables from the module.
    $dumpvars(0,matrixops_tb);

    $display("Simulation started.");
  
    clk = 1;
    rst = 1;
    X = 0;
    Y = 0;
    enter = 0;
    #(FP-1); // To avoid race conditions, modify inputs prior to the clock edge

    rst = 0;
    X = 0;
    Y = 0;
    enter = 1;
    #FP;

    rst = 0;
    X = 0;
    Y = 0;
    enter = 0;
    #FP;

    rst = 0;
    X = 2;
    Y = 0;
    enter = 1;
    #FP;

    rst = 0;
    X = 1;
    Y = 1;
    enter = 1;
    #FP;

    rst = 0;
    X = 1;
    Y = 3;
    enter = 1;
    #FP;

    rst = 0;
    X = 3;
    Y = 3;
    enter = 1;
    #FP;

    rst = 0;
    X = 0;
    Y = 2;
    enter = 1;
    #FP;

    rst = 0;
    X = 1;
    Y = 1;
    enter = 1;
    #FP;

    rst = 0;
    X = 1;
    Y = 1;
    enter = 0;
    #FP;

    rst = 0;
    X = 1;
    Y = 1;
    enter = 0;
    #FP;

    rst = 0;
    X = 0;
    Y = 0;
    enter = 0;
    #FP;

    rst = 0;
    X = 0;
    Y = 0;
    enter = 0;
    #FP;

    rst = 0;
    X = 0;
    Y = 0;
    enter = 1;
    #FP;

    rst = 0;
    X = 1;
    Y = 2;
    enter = 1;
    #FP;

    rst = 0;
    X = 1;
    Y = 2;
    enter = 0;
    #FP;

    $display("Simulation finished.");
    $finish(); // Finish simulation.
  end

endmodule

Matrix_I:O_Operations/matrixops_tb.vcd
$date
	Sat Dec  7 21:27:00 2024
$end
$version
	Icarus Verilog
$end
$timescale
	1s
$end
$scope module matrixops_tb $end
$var wire 1 ! Z $end
$var parameter 64 " FP $end
$var parameter 32 # HP $end
$var reg 2 $ X [1:0] $end
$var reg 2 % Y [1:0] $end
$var reg 1 & clk $end
$var reg 1 ' enter $end
$var reg 1 ( rst $end
$scope module dut $end
$var wire 2 ) X [1:0] $end
$var wire 2 * Y [1:0] $end
$var wire 1 & clk $end
$var wire 1 ' enter $end
$var wire 1 ( rst $end
$var parameter 2 + IN $end
$var parameter 2 , OUT $end
$var parameter 2 - R $end
$var parameter 2 . S $end
$var reg 3 / Cntr [2:0] $end
$var reg 16 0 M [15:0] $end
$var reg 1 ! Z $end
$var reg 2 1 Z_next [1:0] $end
$var reg 2 2 cState [1:0] $end
$var reg 2 3 nState [1:0] $end
$upscope $end
$upscope $end
$enddefinitions $end
$comment Show the parameter values. $end
$dumpall
b1 .
b0 -
b11 ,
b10 +
b101 #
b1010 "
$end
#0
$dumpvars
b1 3
b0 2
b0 1
b0 0
b0 /
b0 *
b0 )
1(
0'
1&
b0 %
b0 $
x!
$end
#5
0&
#9
1'
0(
#10
b10 3
0!
b1 2
1&
#15
0&
#19
0'
#20
b10 2
1&
#25
0&
#29
1'
b10 $
b10 )
#30
b1 /
b100 0
1&
#35
0&
#39
b1 %
b1 *
b1 $
b1 )
#40
b10 /
b100100 0
1&
#45
0&
#49
b11 %
b11 *
#50
b11 /
b10000000100100 0
1&
#55
0&
#59
b11 $
b11 )
#60
b100 /
b1010000000100100 0
1&
#65
0&
#69
b10 %
b10 *
b0 $
b0 )
#70
b11 3
b101 /
b1010000100100100 0
1&
#75
0&
#79
b1 %
b1 *
b1 $
b1 )
#80
b11 2
b1 1
1&
#85
0&
#89
0'
#90
1!
1&
#95
0&
#100
1&
#105
0&
#109
b0 %
b0 *
b0 $
b0 )
#110
1&
#115
0&
#120
1&
#125
0&
#129
1'
#130
b0 1
1&
#135
0&
#139
b10 %
b10 *
b1 $
b1 )
#140
0!
1&
#145
0&
#149
0'
