15BitCarryLookaheadAdderImplementationUsing3BitCLAs/CLA_3bit.v
// DO NOT CHANGE THE INPUT/OUTPUT NAMES, OTHERWISE WE CAN'T GRADE YOUR SUBMISSION

module CLA_3bit (
  input  [2:0] C    ,
  input  [2:0] D    ,
  input        Cin  ,
  input        mode , // 0 --> addition , 1 --> subtraction
  output [2:0] RES  ,
  output       Carry
);

  /* Your design goes here */

  //wires first
  wire [2:0] P, G, D_forsubstraction;
  wire [2:0] carrie; // this is for the carries in between cla s
  
  //propogation and generate assignment
  assign P = C^D;
  assign G = C&D;

  //now the carries for 3 bit cla
  assign carrie[0] = Cin;
  assign carrie[1] = G[0] | (P[0] & carrie[0]);
  assign carrie[2] = G[1] | (P[1] & carrie[1]);
  assign Carry = G[2] | (P[2] & carrie[2]);


  //result
  assign RES = P^carrie;

endmodule

15BitCarryLookaheadAdderImplementationUsing3BitCLAs/CLA_15bit_top.v
// DO NOT CHANGE THE INPUT/OUTPUT NAMES, OTHERWISE WE CAN'T GRADE YOUR SUBMISSION

module CLA_15bit_top (
  input  [14:0] A   ,
  input  [14:0] B   ,
  input         mode, // 0 --> addition , 1 --> subtraction
  output [14:0] S   ,
  output        Cout,
  output        OVF
);

  /* Your design goes here */

  wire [14:0] B_forsubstraction =  B^{15{mode}};
  wire [4:0] carry;

  //xor-ing b with mode to decide addition substraction
  //assign B_forsubstraction = B^{15{mode}};
  assign carry[0] = mode; //first carry is mode

  //now will use 5 of 3 bit cla s
  // we are slicing the bits to pieces of 3 bits each to use in 3 bit cla s
  CLA_3bit cla0 (.C(A[2:0]), .D(B_forsubstraction[2:0]), .Cin(carry[0]), .mode(mode), .RES(S[2:0]), .Carry(carry[1]));
  CLA_3bit cla1 (.C(A[5:3]), .D(B_forsubstraction[5:3]), .Cin(carry[1]), .mode(mode), .RES(S[5:3]), .Carry(carry[2]));
  CLA_3bit cla2 (.C(A[8:6]), .D(B_forsubstraction[8:6]), .Cin(carry[2]), .mode(mode), .RES(S[8:6]), .Carry(carry[3]));
  CLA_3bit cla3 (.C(A[11:9]), .D(B_forsubstraction[11:9]), .Cin(carry[3]), .mode(mode), .RES(S[11:9]), .Carry(carry[4]));
  CLA_3bit cla4 (.C(A[14:12]), .D(B_forsubstraction[14:12]), .Cin(carry[4]), .mode(mode), .RES(S[14:12]), .Carry(Cout));

  //now the way to find overflow
  assign OVF = (A[14] & B_forsubstraction[14] & ~S[14]) | (~A[14] & ~B_forsubstraction[14] & S[14]);

endmodule

15BitCarryLookaheadAdderImplementationUsing3BitCLAs/CLA_15bit_tb.v
// DO NOT CHANGE THE INPUT/OUTPUT NAMES, OTHERWISE WE CAN'T GRADE YOUR SUBMISSION

module CLA_15bit_tb ();

reg  [14:0] A, B; // Inputs
reg         mode; // mode (add or subtract)
wire [14:0] S   ; // result
wire        Ovf ; // Outputs are wires.
wire        Cout;

CLA_15bit_top dut (A,B,mode,S,Cout,Ovf);// Our design-under-test.

initial begin
  //  * Our waveform is saved under this file.

  $dumpfile("CLA_15bit_top.vcd");

  // * Get the variables from the module.

  $dumpvars(0,CLA_15bit_tb);

  $display("Simulation started.");

  //all inputs are zero
  A = 15'd0;  // Set all inputs to zero.
  B = 15'd0;
  mode = 1'd0;
  #10;     // Wait 10 time units.

  //addition without a carry and without an overflow
  A = 15'd25;
  B = 15'd50;
  mode = 1'd0; // For addition
  #10;     // Wait 10 time units.

  //addition without a carry and with an overflow
  A = 15'd8192;
  B = 15'd8192;
  mode = 1'd0;
  #10;

  //addition with a carry and without an overflow
  A = -15'd8192;
  B = -15'd8192;
  mode = 1'd0;
  #10;

  //addition with a carry and with an overflow
  A = -15'd16383;
  B = -15'd16384;
  mode = 1'd0;
  #10;

  //substraction wihtout a carry and without an overflow
  A = 15'd25;
  B = -15'd50;
  mode = 1'd1;
  #10;

  //substraction without a carry and with an overflow
  A = 15'd8192;
  B = -15'd8192;
  mode = 1'd1;
  #10;

  //substraction with a carry and without an overflow
  A = -15'd8192;
  B = 15'd8192;
  mode = 1'd1;
  #10;

 //substraction with a carry and with an overflow
  A = -15'd16382;
  B = 15'd16383;
  mode = 1'd1;
  #10; 
  
  $display("Simulation finished.");
  $finish(); // Finish simulation.
end

endmodule

15BitCarryLookaheadAdderImplementationUsing3BitCLAs/CLA_15bit_top.vcd
$date
	Sun Nov 24 17:51:11 2024
$end
$version
	Icarus Verilog
$end
$timescale
	1s
$end
$scope module CLA_15bit_tb $end
$var wire 15 ! S [14:0] $end
$var wire 1 " Ovf $end
$var wire 1 # Cout $end
$var reg 15 $ A [14:0] $end
$var reg 15 % B [14:0] $end
$var reg 1 & mode $end
$scope module dut $end
$var wire 15 ' A [14:0] $end
$var wire 15 ( B [14:0] $end
$var wire 15 ) B_forsubstraction [14:0] $end
$var wire 1 " OVF $end
$var wire 1 & mode $end
$var wire 5 * carry [4:0] $end
$var wire 15 + S [14:0] $end
$var wire 1 # Cout $end
$scope module cla0 $end
$var wire 3 , C [2:0] $end
$var wire 1 - Carry $end
$var wire 1 . Cin $end
$var wire 3 / D [2:0] $end
$var wire 3 0 G [2:0] $end
$var wire 3 1 P [2:0] $end
$var wire 3 2 RES [2:0] $end
$var wire 1 & mode $end
$var wire 3 3 carrie [2:0] $end
$upscope $end
$scope module cla1 $end
$var wire 3 4 C [2:0] $end
$var wire 1 5 Carry $end
$var wire 1 6 Cin $end
$var wire 3 7 D [2:0] $end
$var wire 3 8 G [2:0] $end
$var wire 3 9 P [2:0] $end
$var wire 3 : RES [2:0] $end
$var wire 1 & mode $end
$var wire 3 ; carrie [2:0] $end
$upscope $end
$scope module cla2 $end
$var wire 3 < C [2:0] $end
$var wire 1 = Carry $end
$var wire 1 > Cin $end
$var wire 3 ? D [2:0] $end
$var wire 3 @ G [2:0] $end
$var wire 3 A P [2:0] $end
$var wire 3 B RES [2:0] $end
$var wire 1 & mode $end
$var wire 3 C carrie [2:0] $end
$upscope $end
$scope module cla3 $end
$var wire 3 D C [2:0] $end
$var wire 1 E Carry $end
$var wire 1 F Cin $end
$var wire 3 G D [2:0] $end
$var wire 3 H G [2:0] $end
$var wire 3 I P [2:0] $end
$var wire 3 J RES [2:0] $end
$var wire 1 & mode $end
$var wire 3 K carrie [2:0] $end
$upscope $end
$scope module cla4 $end
$var wire 3 L C [2:0] $end
$var wire 1 # Carry $end
$var wire 1 M Cin $end
$var wire 3 N D [2:0] $end
$var wire 3 O G [2:0] $end
$var wire 3 P P [2:0] $end
$var wire 3 Q RES [2:0] $end
$var wire 1 & mode $end
$var wire 3 R carrie [2:0] $end
$upscope $end
$upscope $end
$upscope $end
$enddefinitions $end
$comment Show the parameter values. $end
$dumpall
$end
#0
$dumpvars
b0 R
b0 Q
b0 P
b0 O
b0 N
0M
b0 L
b0 K
b0 J
b0 I
b0 H
b0 G
0F
0E
b0 D
b0 C
b0 B
b0 A
b0 @
b0 ?
0>
0=
b0 <
b0 ;
b0 :
b0 9
b0 8
b0 7
06
05
b0 4
b0 3
b0 2
b0 1
b0 0
b0 /
0.
0-
b0 ,
b0 +
b0 *
b0 )
b0 (
b0 '
0&
b0 %
b0 $
0#
0"
b0 !
$end
#10
b1 B
b1 C
1>
b100 *
15
b100 ;
b10 8
b11 2
b1001011 !
b1001011 +
b1 :
b10 /
b110 7
b11 1
b101 9
b110010 )
b1 ,
b11 4
b110010 %
b110010 (
b11001 $
b11001 '
#20
1"
b0 B
b0 C
0>
b0 *
05
b100 R
b0 ;
b10 O
b0 2
b0 :
b100000000000000 !
b100000000000000 +
b100 Q
b0 /
b0 7
b10 N
b0 1
b0 9
b0 8
b0 P
b10000000000000 )
b0 ,
b0 4
b10 L
b10000000000000 %
b10000000000000 (
b10000000000000 $
b10000000000000 '
#30
1#
0"
b110 O
b100000000000000 !
b100000000000000 +
b100 Q
b110 N
b0 P
b110000000000000 )
b110 L
b110000000000000 %
b110000000000000 (
b110000000000000 $
b110000000000000 '
#40
1"
b0 R
b1 2
b1 !
b1 +
b0 Q
b100 N
b1 1
b0 P
b100 O
b100000000000000 )
b1 ,
b100 L
b100000000000000 %
b100000000000000 (
b100000000000001 $
b100000000000001 '
#50
b1 B
b1 C
1>
15
b100 ;
0#
0"
b0 1
b1 0
b10 8
b1 :
b0 Q
b1001011 !
b1001011 +
b11 2
b1 /
b110 7
b0 N
b101 9
b0 P
b0 O
b11 3
1.
b110001 )
b11 4
b0 L
b101 *
1&
b111111111001110 %
b111111111001110 (
b11001 $
b11001 '
#60
1"
b111 R
1M
1E
b111 K
1F
1=
16
1-
1>
b11111 *
15
b111 C
b0 B
b0 J
b111 3
b111 ;
b111 A
b111 I
b0 2
b0 :
b100000000000000 !
b100000000000000 +
b100 Q
b111 /
b111 7
b111 ?
b111 G
b1 N
b111 1
b0 0
b111 9
b0 8
b11 P
b1111111111111 )
b0 ,
b0 4
b10 L
b110000000000000 %
b110000000000000 (
b10000000000000 $
b10000000000000 '
#70
1#
0"
b100 O
b100000000000000 !
b100000000000000 +
b100 Q
b101 N
b11 P
b101111111111111 )
b110 L
b10000000000000 %
b10000000000000 (
b110000000000000 $
b110000000000000 '
#80
1"
06
0>
0F
0M
0-
b0 ;
05
b0 C
0=
b0 K
b1 *
0E
b1 3
b0 R
b0 :
b0 B
b0 J
b0 9
b0 A
b0 I
b11 2
b11 !
b11 +
b0 Q
b0 /
b0 7
b0 ?
b0 G
b100 N
b10 1
b0 0
b0 P
b100000000000000 )
b10 ,
b100 L
b11111111111111 %
b11111111111111 (
b100000000000010 $
b100000000000010 '
